hindikosh/HindiTokenizer.py
hindikosh/__init__.py
hindikosh/reader.py
hindikosh-0.0.1.dist-info/DESCRIPTION.rst
hindikosh-0.0.1.dist-info/METADATA
hindikosh-0.0.1.dist-info/RECORD
hindikosh-0.0.1.dist-info/WHEEL
hindikosh-0.0.1.dist-info/metadata.json
hindikosh-0.0.1.dist-info/top_level.txt
kush/HindiTokenizer.py
kush/__init__.py
kush/reader.py
